main.py
pt_config.py
pt_crypto.py
pt_init.py
pytinel-0.1.4.dist-info/licenses/LICENSE
pytinel-0.1.4.dist-info/METADATA
pytinel-0.1.4.dist-info/WHEEL
pytinel-0.1.4.dist-info/entry_points.txt
pytinel-0.1.4.dist-info/top_level.txt
pytinel-0.1.4.dist-info/RECORD
