Metadata-Version: 2.4
Name: pytinel
Version: 0.1.4
Summary: Python Terminal in Natural Executable Language - AI-powered Python REPL terminal
Author-email: miller-owo <mellerowo@gmail.com>
License: MIT License
Project-URL: Homepage, https://github.com/miller-owo/pytinel
Project-URL: Repository, https://github.com/miller-owo/pytinel.git
Classifier: Programming Language :: Python :: 3
Classifier: Programming Language :: Python :: 3.7
Classifier: Programming Language :: Python :: 3.8
Classifier: Programming Language :: Python :: 3.9
Classifier: Programming Language :: Python :: 3.10
Classifier: Programming Language :: Python :: 3.11
Classifier: License :: OSI Approved :: MIT License
Classifier: Operating System :: OS Independent
Classifier: Intended Audience :: Developers
Classifier: Topic :: Software Development :: Interpreters
Requires-Python: >=3.7
License-File: LICENSE
Requires-Dist: requests<3.0.0,>=2.28.0
Requires-Dist: platformdirs<5.0.0,>=3.5.0
Requires-Dist: cryptography<42.0.0,>=40.0.0
Dynamic: license-file
